ok_images/__init__.py
ok_images/admin.py
ok_images/consts.py
ok_images/fields.py
ok_images/files.py
ok_images/models.py
ok_images/utils.py
ok_images/validators.py
ok_images/contrib/__init__.py
ok_images/contrib/rest_framework/__init__.py
ok_images/contrib/rest_framework/fields.py
ok_images/contrib/versatileimagefield/__init__.py
ok_images/contrib/versatileimagefield/utils.py
ok_images/contrib/versatileimagefield/versatileimagefield.py
django_ok_images-0.1.8.dist-info/LICENSE
django_ok_images-0.1.8.dist-info/METADATA
django_ok_images-0.1.8.dist-info/WHEEL
django_ok_images-0.1.8.dist-info/top_level.txt
django_ok_images-0.1.8.dist-info/RECORD
