Metadata-Version: 2.1
Name: django-ok-images
Version: 0.1.8
Summary: django-ok-images allows to generate WebP images using django-versatileimagefield.
Home-page: https://github.com/LowerDeez/ok-images
Author: Oleg Kleschunov
Author-email: igorkleschunov@gmail.com
License: MIT
Keywords: python,images,image-models,django,webp,django-versatileimagefield
Platform: UNKNOWN
Classifier: Development Status :: 4 - Beta
Classifier: Environment :: Web Environment
Classifier: Intended Audience :: Developers
Classifier: License :: OSI Approved :: MIT License
Classifier: Operating System :: OS Independent
Classifier: Programming Language :: Python
Classifier: Programming Language :: Python :: 3.6
Classifier: Programming Language :: Python :: 3.7
Classifier: Framework :: Django
Classifier: Framework :: Django :: 1.11
Classifier: Framework :: Django :: 2.0
Classifier: Framework :: Django :: 2.1
Classifier: Framework :: Django :: 2.2
License-File: LICENSE
Requires-Dist: django (>=1.11)
Requires-Dist: six
Requires-Dist: mock
